zodchy_security/__init__.py
zodchy_security/authorization/__init__.py
zodchy_security/authorization/audit.py
zodchy_security/credentials/__init__.py
zodchy_security/credentials/otp.py
zodchy_security/tokens/__init__.py
zodchy_security/tokens/jwts.py
zodchy_security-0.2.1.dist-info/METADATA
zodchy_security-0.2.1.dist-info/WHEEL
zodchy_security-0.2.1.dist-info/RECORD
